simplesvm/__about__.py
simplesvm/__init__.py
simplesvm/kernel_svm.py
simplesvm/linear_svm.py
simplesvm-0.0.6.dist-info/METADATA
simplesvm-0.0.6.dist-info/WHEEL
simplesvm-0.0.6.dist-info/licenses/LICENSE
simplesvm-0.0.6.dist-info/RECORD
