Metadata-Version: 2.3
Name: simplesvm
Version: 0.0.6
Summary: A simple Support Vector Machine for Binary Classification.
Project-URL: Documentation, https://github.com/obizip/simplesvm#readme
Project-URL: Issues, https://github.com/obizip/simplesvm/issues
Project-URL: Source, https://github.com/obizip/simplesvm
Author-email: obizip <ct4kuto@gmail.com>
License-Expression: MIT
License-File: LICENSE
Classifier: Development Status :: 4 - Beta
Classifier: Programming Language :: Python
Classifier: Programming Language :: Python :: 3.9
Classifier: Programming Language :: Python :: 3.10
Classifier: Programming Language :: Python :: 3.11
Classifier: Programming Language :: Python :: 3.12
Classifier: Programming Language :: Python :: Implementation :: CPython
Classifier: Programming Language :: Python :: Implementation :: PyPy
Requires-Python: >=3.9
Requires-Dist: numpy>=1.19.5
